{
    "processed": [
        {
            "file": {
                "name": "NotoSerifHebrew-CondensedThin.ttf",
                "type": "ttf",
                "size": 21316,
                "md5": "da8111b73695a45328ab87d2ce19fb07",
                "geometryMd5": "9861626b976b91802af0ef431bd24308"
            },
            "name": {
                "family": "Noto Serif Hebrew Cond Thin",
                "subFamily": "Regular",
                "fullName": "Noto Serif Hebrew Condensed Thin",
                "psName": "NotoSerifHebrew-CondensedThin",
                "versionText": "Version 2.000;GOOG;noto-source:20170915:90ef993387c0",
                "copyright": "Copyright 2016 Google Inc. All Rights Reserved.",
                "trademark": "Noto is a trademark of Google Inc.",
                "typographicFamily": "Noto Serif Hebrew",
                "typographicSubFamily": "Condensed Thin"
            },
            "format": {
                "format": "OT",
                "flavor": "TT"
            },
            "summary": {
                "num_glyphs": 150,
                "embedding": "Installable Embedding",
                "font_vendor_id": "GOOG",
                "font_vendor": "Google"
            },
            "validation": {
                "font_full_name": "Noto Serif Hebrew Condensed Thin",
                "level": "ERROR",
                "last_success": "finished validation python",
                "msg_count": {
                    "CRITICAL": 0,
                    "ERROR": 1,
                    "WARNING": 0,
                    "INFO": 0,
                    "DEBUG": 0
                },
                "result": [
                    {
                        "subroutine": "validate_0fd80380114042bd8696ad471869b369.name",
                        "levelname": "ERROR",
                        "message": "Postscript name not present for both Mac and Windows.",
                        "timestamp": "2020-09-26T15:31:17.046141Z",
                        "orig_output": "validate_0fd80380114042bd8696ad471869b369.name - ERROR - Postscript name not present for both Mac and Windows.",
                        "msg_code": "E2008"
                    }
                ]
            }
        }
    ],
    "skipped": [],
    "fontio3_version": "3.7.20200604.317848rc4",
    "fontvalidator_version": "20200305.1",
    "runningTime": 7846,
    "completedDate": "2020-09-26 15:31:17.358808"
}