{
    "processed": [
        {
            "file": {
                "name": "ElMessiri-SemiBold.ttf",
                "type": "ttf",
                "size": 121736,
                "md5": "b93a5cb32ef843854c509c9c87c8c980",
                "geometryMd5": "6e9582182cbfd22ba741582db618a1be"
            },
            "name": {
                "family": "El Messiri SemiBold",
                "subFamily": "Regular",
                "fullName": "El Messiri SemiBold",
                "psName": "ElMessiri-SemiBold",
                "versionText": "Version 2.007",
                "copyright": "Copyright 2015 The El Messiri Project Authors.",
                "trademark": "Unknown",
                "typographicFamily": "El Messiri",
                "typographicSubFamily": "SemiBold"
            },
            "format": {
                "format": "OT",
                "flavor": "TT"
            },
            "summary": {
                "num_glyphs": 642,
                "embedding": "Installable Embedding",
                "font_vendor_id": "1KTF",
                "font_vendor": "Kief Type Foundry"
            },
            "validation": {
                "font_full_name": "El Messiri SemiBold",
                "level": "ERROR",
                "last_success": "finished validation python",
                "msg_count": {
                    "CRITICAL": 0,
                    "ERROR": 35,
                    "WARNING": 0,
                    "INFO": 0,
                    "DEBUG": 0
                },
                "result": [
                    {
                        "subroutine": "validate_aba739af13bb4e9399e4974f9fd94e7b.fontedit.OS_2.PANOSE.weight",
                        "levelname": "ERROR",
                        "message": "Value 7 is not a valid enum value. 0 will be used instead, but the font should be fixed.",
                        "timestamp": "2020-09-25T06:20:38.946502Z",
                        "orig_output": "validate_aba739af13bb4e9399e4974f9fd94e7b.fontedit.OS_2.PANOSE.weight - ERROR - Value 7 is not a valid enum value. 0 will be used instead, but the font should be fixed.",
                        "msg_code": "E2111"
                    },
                    {
                        "subroutine": "validate_aba739af13bb4e9399e4974f9fd94e7b.glyf.glyph 427 ('uniFECB').contours.contour 2",
                        "levelname": "ERROR",
                        "message": "Contour is degenerate (only two (x,y) locations).",
                        "timestamp": "2020-09-25T06:20:45.984907Z",
                        "orig_output": "validate_aba739af13bb4e9399e4974f9fd94e7b.glyf.glyph 427 ('uniFECB').contours.contour 2 - ERROR - Contour is degenerate (only two (x,y) locations).",
                        "msg_code": "V1013"
                    },
                    {
                        "subroutine": "validate_aba739af13bb4e9399e4974f9fd94e7b.hmtx",
                        "levelname": "ERROR",
                        "message": "The left sidebearing -44 does not match the glyph's xMin -46 (glyph 394)",
                        "timestamp": "2020-09-25T06:20:51.568417Z",
                        "orig_output": "validate_aba739af13bb4e9399e4974f9fd94e7b.hmtx - ERROR - The left sidebearing -44 does not match the glyph's xMin -46 (glyph 394)",
                        "msg_code": "V0933"
                    },
                    {
                        "subroutine": "validate_aba739af13bb4e9399e4974f9fd94e7b.hmtx",
                        "levelname": "ERROR",
                        "message": "The left sidebearing -44 does not match the glyph's xMin -46 (glyph 395)",
                        "timestamp": "2020-09-25T06:20:51.568907Z",
                        "orig_output": "validate_aba739af13bb4e9399e4974f9fd94e7b.hmtx - ERROR - The left sidebearing -44 does not match the glyph's xMin -46 (glyph 395)",
                        "msg_code": "V0933"
                    },
                    {
                        "subroutine": "validate_aba739af13bb4e9399e4974f9fd94e7b.hmtx",
                        "levelname": "ERROR",
                        "message": "The left sidebearing -44 does not match the glyph's xMin -46 (glyph 396)",
                        "timestamp": "2020-09-25T06:20:51.569329Z",
                        "orig_output": "validate_aba739af13bb4e9399e4974f9fd94e7b.hmtx - ERROR - The left sidebearing -44 does not match the glyph's xMin -46 (glyph 396)",
                        "msg_code": "V0933"
                    },
                    {
                        "subroutine": "validate_aba739af13bb4e9399e4974f9fd94e7b.hmtx",
                        "levelname": "ERROR",
                        "message": "The left sidebearing -44 does not match the glyph's xMin -46 (glyph 397)",
                        "timestamp": "2020-09-25T06:20:51.569740Z",
                        "orig_output": "validate_aba739af13bb4e9399e4974f9fd94e7b.hmtx - ERROR - The left sidebearing -44 does not match the glyph's xMin -46 (glyph 397)",
                        "msg_code": "V0933"
                    },
                    {
                        "subroutine": "validate_aba739af13bb4e9399e4974f9fd94e7b.hmtx",
                        "levelname": "ERROR",
                        "message": "The left sidebearing -44 does not match the glyph's xMin -46 (glyph 398)",
                        "timestamp": "2020-09-25T06:20:51.570160Z",
                        "orig_output": "validate_aba739af13bb4e9399e4974f9fd94e7b.hmtx - ERROR - The left sidebearing -44 does not match the glyph's xMin -46 (glyph 398)",
                        "msg_code": "V0933"
                    },
                    {
                        "subroutine": "validate_aba739af13bb4e9399e4974f9fd94e7b.hmtx",
                        "levelname": "ERROR",
                        "message": "The left sidebearing -44 does not match the glyph's xMin -46 (glyph 399)",
                        "timestamp": "2020-09-25T06:20:51.570592Z",
                        "orig_output": "validate_aba739af13bb4e9399e4974f9fd94e7b.hmtx - ERROR - The left sidebearing -44 does not match the glyph's xMin -46 (glyph 399)",
                        "msg_code": "V0933"
                    },
                    {
                        "subroutine": "validate_aba739af13bb4e9399e4974f9fd94e7b.hmtx",
                        "levelname": "ERROR",
                        "message": "The left sidebearing -44 does not match the glyph's xMin -46 (glyph 535)",
                        "timestamp": "2020-09-25T06:20:51.688810Z",
                        "orig_output": "validate_aba739af13bb4e9399e4974f9fd94e7b.hmtx - ERROR - The left sidebearing -44 does not match the glyph's xMin -46 (glyph 535)",
                        "msg_code": "V0933"
                    },
                    {
                        "subroutine": "validate_aba739af13bb4e9399e4974f9fd94e7b.hmtx",
                        "levelname": "ERROR",
                        "message": "The left sidebearing -44 does not match the glyph's xMin -46 (glyph 536)",
                        "timestamp": "2020-09-25T06:20:51.689420Z",
                        "orig_output": "validate_aba739af13bb4e9399e4974f9fd94e7b.hmtx - ERROR - The left sidebearing -44 does not match the glyph's xMin -46 (glyph 536)",
                        "msg_code": "V0933"
                    },
                    {
                        "subroutine": "validate_aba739af13bb4e9399e4974f9fd94e7b.hmtx",
                        "levelname": "ERROR",
                        "message": "The left sidebearing -44 does not match the glyph's xMin -46 (glyph 537)",
                        "timestamp": "2020-09-25T06:20:51.689838Z",
                        "orig_output": "validate_aba739af13bb4e9399e4974f9fd94e7b.hmtx - ERROR - The left sidebearing -44 does not match the glyph's xMin -46 (glyph 537)",
                        "msg_code": "V0933"
                    },
                    {
                        "subroutine": "validate_aba739af13bb4e9399e4974f9fd94e7b.hmtx",
                        "levelname": "ERROR",
                        "message": "The left sidebearing -44 does not match the glyph's xMin -46 (glyph 538)",
                        "timestamp": "2020-09-25T06:20:51.690411Z",
                        "orig_output": "validate_aba739af13bb4e9399e4974f9fd94e7b.hmtx - ERROR - The left sidebearing -44 does not match the glyph's xMin -46 (glyph 538)",
                        "msg_code": "V0933"
                    },
                    {
                        "subroutine": "validate_aba739af13bb4e9399e4974f9fd94e7b.hmtx",
                        "levelname": "ERROR",
                        "message": "The left sidebearing -44 does not match the glyph's xMin -46 (glyph 539)",
                        "timestamp": "2020-09-25T06:20:51.690824Z",
                        "orig_output": "validate_aba739af13bb4e9399e4974f9fd94e7b.hmtx - ERROR - The left sidebearing -44 does not match the glyph's xMin -46 (glyph 539)",
                        "msg_code": "V0933"
                    },
                    {
                        "subroutine": "validate_aba739af13bb4e9399e4974f9fd94e7b.hmtx",
                        "levelname": "ERROR",
                        "message": "The left sidebearing -44 does not match the glyph's xMin -46 (glyph 540)",
                        "timestamp": "2020-09-25T06:20:51.691380Z",
                        "orig_output": "validate_aba739af13bb4e9399e4974f9fd94e7b.hmtx - ERROR - The left sidebearing -44 does not match the glyph's xMin -46 (glyph 540)",
                        "msg_code": "V0933"
                    },
                    {
                        "subroutine": "validate_aba739af13bb4e9399e4974f9fd94e7b.hmtx",
                        "levelname": "ERROR",
                        "message": "The left sidebearing -44 does not match the glyph's xMin -46 (glyph 541)",
                        "timestamp": "2020-09-25T06:20:51.691790Z",
                        "orig_output": "validate_aba739af13bb4e9399e4974f9fd94e7b.hmtx - ERROR - The left sidebearing -44 does not match the glyph's xMin -46 (glyph 541)",
                        "msg_code": "V0933"
                    },
                    {
                        "subroutine": "validate_aba739af13bb4e9399e4974f9fd94e7b.hmtx",
                        "levelname": "ERROR",
                        "message": "The left sidebearing -44 does not match the glyph's xMin -46 (glyph 542)",
                        "timestamp": "2020-09-25T06:20:51.692346Z",
                        "orig_output": "validate_aba739af13bb4e9399e4974f9fd94e7b.hmtx - ERROR - The left sidebearing -44 does not match the glyph's xMin -46 (glyph 542)",
                        "msg_code": "V0933"
                    },
                    {
                        "subroutine": "validate_aba739af13bb4e9399e4974f9fd94e7b.hmtx",
                        "levelname": "ERROR",
                        "message": "The left sidebearing -44 does not match the glyph's xMin -46 (glyph 545)",
                        "timestamp": "2020-09-25T06:20:51.693968Z",
                        "orig_output": "validate_aba739af13bb4e9399e4974f9fd94e7b.hmtx - ERROR - The left sidebearing -44 does not match the glyph's xMin -46 (glyph 545)",
                        "msg_code": "V0933"
                    },
                    {
                        "subroutine": "validate_aba739af13bb4e9399e4974f9fd94e7b.hmtx",
                        "levelname": "ERROR",
                        "message": "The left sidebearing -44 does not match the glyph's xMin -46 (glyph 546)",
                        "timestamp": "2020-09-25T06:20:51.694395Z",
                        "orig_output": "validate_aba739af13bb4e9399e4974f9fd94e7b.hmtx - ERROR - The left sidebearing -44 does not match the glyph's xMin -46 (glyph 546)",
                        "msg_code": "V0933"
                    },
                    {
                        "subroutine": "validate_aba739af13bb4e9399e4974f9fd94e7b.hmtx",
                        "levelname": "ERROR",
                        "message": "The left sidebearing -44 does not match the glyph's xMin -46 (glyph 547)",
                        "timestamp": "2020-09-25T06:20:51.694817Z",
                        "orig_output": "validate_aba739af13bb4e9399e4974f9fd94e7b.hmtx - ERROR - The left sidebearing -44 does not match the glyph's xMin -46 (glyph 547)",
                        "msg_code": "V0933"
                    },
                    {
                        "subroutine": "validate_aba739af13bb4e9399e4974f9fd94e7b.hmtx",
                        "levelname": "ERROR",
                        "message": "The left sidebearing -44 does not match the glyph's xMin -46 (glyph 548)",
                        "timestamp": "2020-09-25T06:20:51.695237Z",
                        "orig_output": "validate_aba739af13bb4e9399e4974f9fd94e7b.hmtx - ERROR - The left sidebearing -44 does not match the glyph's xMin -46 (glyph 548)",
                        "msg_code": "V0933"
                    },
                    {
                        "subroutine": "validate_aba739af13bb4e9399e4974f9fd94e7b.hmtx",
                        "levelname": "ERROR",
                        "message": "The left sidebearing -44 does not match the glyph's xMin -46 (glyph 549)",
                        "timestamp": "2020-09-25T06:20:51.695785Z",
                        "orig_output": "validate_aba739af13bb4e9399e4974f9fd94e7b.hmtx - ERROR - The left sidebearing -44 does not match the glyph's xMin -46 (glyph 549)",
                        "msg_code": "V0933"
                    },
                    {
                        "subroutine": "validate_aba739af13bb4e9399e4974f9fd94e7b.hmtx",
                        "levelname": "ERROR",
                        "message": "The left sidebearing -44 does not match the glyph's xMin -46 (glyph 550)",
                        "timestamp": "2020-09-25T06:20:51.696360Z",
                        "orig_output": "validate_aba739af13bb4e9399e4974f9fd94e7b.hmtx - ERROR - The left sidebearing -44 does not match the glyph's xMin -46 (glyph 550)",
                        "msg_code": "V0933"
                    },
                    {
                        "subroutine": "validate_aba739af13bb4e9399e4974f9fd94e7b.hmtx",
                        "levelname": "ERROR",
                        "message": "The left sidebearing -44 does not match the glyph's xMin -46 (glyph 553)",
                        "timestamp": "2020-09-25T06:20:51.697678Z",
                        "orig_output": "validate_aba739af13bb4e9399e4974f9fd94e7b.hmtx - ERROR - The left sidebearing -44 does not match the glyph's xMin -46 (glyph 553)",
                        "msg_code": "V0933"
                    },
                    {
                        "subroutine": "validate_aba739af13bb4e9399e4974f9fd94e7b.hmtx",
                        "levelname": "ERROR",
                        "message": "The left sidebearing -44 does not match the glyph's xMin -46 (glyph 554)",
                        "timestamp": "2020-09-25T06:20:51.698107Z",
                        "orig_output": "validate_aba739af13bb4e9399e4974f9fd94e7b.hmtx - ERROR - The left sidebearing -44 does not match the glyph's xMin -46 (glyph 554)",
                        "msg_code": "V0933"
                    },
                    {
                        "subroutine": "validate_aba739af13bb4e9399e4974f9fd94e7b.hmtx",
                        "levelname": "ERROR",
                        "message": "The left sidebearing -44 does not match the glyph's xMin -46 (glyph 555)",
                        "timestamp": "2020-09-25T06:20:51.710627Z",
                        "orig_output": "validate_aba739af13bb4e9399e4974f9fd94e7b.hmtx - ERROR - The left sidebearing -44 does not match the glyph's xMin -46 (glyph 555)",
                        "msg_code": "V0933"
                    },
                    {
                        "subroutine": "validate_aba739af13bb4e9399e4974f9fd94e7b.hmtx",
                        "levelname": "ERROR",
                        "message": "The left sidebearing -44 does not match the glyph's xMin -46 (glyph 556)",
                        "timestamp": "2020-09-25T06:20:51.711089Z",
                        "orig_output": "validate_aba739af13bb4e9399e4974f9fd94e7b.hmtx - ERROR - The left sidebearing -44 does not match the glyph's xMin -46 (glyph 556)",
                        "msg_code": "V0933"
                    },
                    {
                        "subroutine": "validate_aba739af13bb4e9399e4974f9fd94e7b.hmtx",
                        "levelname": "ERROR",
                        "message": "The left sidebearing -44 does not match the glyph's xMin -46 (glyph 557)",
                        "timestamp": "2020-09-25T06:20:51.711660Z",
                        "orig_output": "validate_aba739af13bb4e9399e4974f9fd94e7b.hmtx - ERROR - The left sidebearing -44 does not match the glyph's xMin -46 (glyph 557)",
                        "msg_code": "V0933"
                    },
                    {
                        "subroutine": "validate_aba739af13bb4e9399e4974f9fd94e7b.hmtx",
                        "levelname": "ERROR",
                        "message": "The left sidebearing -44 does not match the glyph's xMin -46 (glyph 558)",
                        "timestamp": "2020-09-25T06:20:51.712206Z",
                        "orig_output": "validate_aba739af13bb4e9399e4974f9fd94e7b.hmtx - ERROR - The left sidebearing -44 does not match the glyph's xMin -46 (glyph 558)",
                        "msg_code": "V0933"
                    },
                    {
                        "subroutine": "validate_aba739af13bb4e9399e4974f9fd94e7b.hmtx",
                        "levelname": "ERROR",
                        "message": "The left sidebearing -44 does not match the glyph's xMin -46 (glyph 559)",
                        "timestamp": "2020-09-25T06:20:51.712608Z",
                        "orig_output": "validate_aba739af13bb4e9399e4974f9fd94e7b.hmtx - ERROR - The left sidebearing -44 does not match the glyph's xMin -46 (glyph 559)",
                        "msg_code": "V0933"
                    },
                    {
                        "subroutine": "validate_aba739af13bb4e9399e4974f9fd94e7b.hmtx",
                        "levelname": "ERROR",
                        "message": "The left sidebearing -44 does not match the glyph's xMin -46 (glyph 560)",
                        "timestamp": "2020-09-25T06:20:51.713164Z",
                        "orig_output": "validate_aba739af13bb4e9399e4974f9fd94e7b.hmtx - ERROR - The left sidebearing -44 does not match the glyph's xMin -46 (glyph 560)",
                        "msg_code": "V0933"
                    },
                    {
                        "subroutine": "validate_aba739af13bb4e9399e4974f9fd94e7b.hmtx",
                        "levelname": "ERROR",
                        "message": "The left sidebearing -44 does not match the glyph's xMin -46 (glyph 562)",
                        "timestamp": "2020-09-25T06:20:51.713925Z",
                        "orig_output": "validate_aba739af13bb4e9399e4974f9fd94e7b.hmtx - ERROR - The left sidebearing -44 does not match the glyph's xMin -46 (glyph 562)",
                        "msg_code": "V0933"
                    },
                    {
                        "subroutine": "validate_aba739af13bb4e9399e4974f9fd94e7b.hmtx",
                        "levelname": "ERROR",
                        "message": "The left sidebearing -44 does not match the glyph's xMin -46 (glyph 563)",
                        "timestamp": "2020-09-25T06:20:51.714371Z",
                        "orig_output": "validate_aba739af13bb4e9399e4974f9fd94e7b.hmtx - ERROR - The left sidebearing -44 does not match the glyph's xMin -46 (glyph 563)",
                        "msg_code": "V0933"
                    },
                    {
                        "subroutine": "validate_aba739af13bb4e9399e4974f9fd94e7b.hmtx",
                        "levelname": "ERROR",
                        "message": "The left sidebearing -44 does not match the glyph's xMin -46 (glyph 564)",
                        "timestamp": "2020-09-25T06:20:51.714919Z",
                        "orig_output": "validate_aba739af13bb4e9399e4974f9fd94e7b.hmtx - ERROR - The left sidebearing -44 does not match the glyph's xMin -46 (glyph 564)",
                        "msg_code": "V0933"
                    },
                    {
                        "subroutine": "validate_aba739af13bb4e9399e4974f9fd94e7b.hmtx",
                        "levelname": "ERROR",
                        "message": "The left sidebearing -44 does not match the glyph's xMin -46 (glyph 565)",
                        "timestamp": "2020-09-25T06:20:51.715320Z",
                        "orig_output": "validate_aba739af13bb4e9399e4974f9fd94e7b.hmtx - ERROR - The left sidebearing -44 does not match the glyph's xMin -46 (glyph 565)",
                        "msg_code": "V0933"
                    },
                    {
                        "subroutine": "validate_aba739af13bb4e9399e4974f9fd94e7b.hmtx",
                        "levelname": "ERROR",
                        "message": "The left sidebearing -44 does not match the glyph's xMin -46 (glyph 566)",
                        "timestamp": "2020-09-25T06:20:51.715853Z",
                        "orig_output": "validate_aba739af13bb4e9399e4974f9fd94e7b.hmtx - ERROR - The left sidebearing -44 does not match the glyph's xMin -46 (glyph 566)",
                        "msg_code": "V0933"
                    }
                ]
            }
        }
    ],
    "skipped": [],
    "fontio3_version": "3.7.20200604.317848rc4",
    "fontvalidator_version": "20200305.1",
    "runningTime": 141311,
    "completedDate": "2020-09-25 06:22:57.408088"
}