{
    "processed": [
        {
            "file": {
                "name": "JosefinSlab-LightItalic.ttf",
                "type": "ttf",
                "size": 159936,
                "md5": "e4ecc8cd6b93fdf9eeaa99582d584060",
                "geometryMd5": "68b45dcc5e3c815ecbe4947c3436bc5b"
            },
            "name": {
                "family": "Josefin Slab Light",
                "subFamily": "Italic",
                "fullName": "Josefin Slab Light Italic",
                "psName": "JosefinSlab-LightItalic",
                "versionText": "Version 1.001",
                "copyright": "Copyright (c) 2010 by Typemade. All rights reserved.",
                "trademark": "Josefin Slab Light Italic is a trademark of Typemade.",
                "typographicFamily": "Josefin Slab",
                "typographicSubFamily": "Light Italic"
            },
            "format": {
                "format": "TT"
            },
            "summary": {
                "num_glyphs": 206,
                "embedding": "Installable Embedding",
                "font_vendor_id": "    ",
                "font_vendor": "Unknown"
            },
            "validation": {
                "font_full_name": "Josefin Slab Light Italic",
                "level": "ERROR",
                "last_success": "finished validation python",
                "msg_count": {
                    "CRITICAL": 0,
                    "ERROR": 150,
                    "WARNING": 0,
                    "INFO": 0,
                    "DEBUG": 0
                },
                "result": [
                    {
                        "subroutine": "validate_c1833fdedee0408380c9a059c958948a.glyf.glyph 100 ('cent').contours.contour 0",
                        "levelname": "ERROR",
                        "message": "Contour has duplicate adjacent points of differing on-curve states.",
                        "timestamp": "2020-09-24T21:01:01.466205Z",
                        "orig_output": "validate_c1833fdedee0408380c9a059c958948a.glyf.glyph 100 ('cent').contours.contour 0 - ERROR - Contour has duplicate adjacent points of differing on-curve states.",
                        "msg_code": "V0295"
                    },
                    {
                        "subroutine": "validate_c1833fdedee0408380c9a059c958948a.hdmx.10 ppem",
                        "levelname": "ERROR",
                        "message": "Glyph 47's value should be 6, but is 5",
                        "timestamp": "2020-09-24T21:01:02.838657Z",
                        "orig_output": "validate_c1833fdedee0408380c9a059c958948a.hdmx.10 ppem - ERROR - Glyph 47's value should be 6, but is 5",
                        "msg_code": "E1207"
                    },
                    {
                        "subroutine": "validate_c1833fdedee0408380c9a059c958948a.hdmx.10 ppem",
                        "levelname": "ERROR",
                        "message": "Glyph 48's value should be 10, but is 9",
                        "timestamp": "2020-09-24T21:01:02.838725Z",
                        "orig_output": "validate_c1833fdedee0408380c9a059c958948a.hdmx.10 ppem - ERROR - Glyph 48's value should be 10, but is 9",
                        "msg_code": "E1207"
                    },
                    {
                        "subroutine": "validate_c1833fdedee0408380c9a059c958948a.hdmx.10 ppem",
                        "levelname": "ERROR",
                        "message": "Glyph 55's value should be 6, but is 7",
                        "timestamp": "2020-09-24T21:01:02.838779Z",
                        "orig_output": "validate_c1833fdedee0408380c9a059c958948a.hdmx.10 ppem - ERROR - Glyph 55's value should be 6, but is 7",
                        "msg_code": "E1207"
                    },
                    {
                        "subroutine": "validate_c1833fdedee0408380c9a059c958948a.hdmx.11 ppem",
                        "levelname": "ERROR",
                        "message": "Glyph 7's value should be 6, but is 7",
                        "timestamp": "2020-09-24T21:01:02.839921Z",
                        "orig_output": "validate_c1833fdedee0408380c9a059c958948a.hdmx.11 ppem - ERROR - Glyph 7's value should be 6, but is 7",
                        "msg_code": "E1207"
                    },
                    {
                        "subroutine": "validate_c1833fdedee0408380c9a059c958948a.hdmx.11 ppem",
                        "levelname": "ERROR",
                        "message": "Glyph 46's value should be 8, but is 7",
                        "timestamp": "2020-09-24T21:01:02.840000Z",
                        "orig_output": "validate_c1833fdedee0408380c9a059c958948a.hdmx.11 ppem - ERROR - Glyph 46's value should be 8, but is 7",
                        "msg_code": "E1207"
                    },
                    {
                        "subroutine": "validate_c1833fdedee0408380c9a059c958948a.hdmx.11 ppem",
                        "levelname": "ERROR",
                        "message": "Glyph 51's value should be 5, but is 6",
                        "timestamp": "2020-09-24T21:01:02.840054Z",
                        "orig_output": "validate_c1833fdedee0408380c9a059c958948a.hdmx.11 ppem - ERROR - Glyph 51's value should be 5, but is 6",
                        "msg_code": "E1207"
                    },
                    {
                        "subroutine": "validate_c1833fdedee0408380c9a059c958948a.hdmx.11 ppem",
                        "levelname": "ERROR",
                        "message": "Glyph 100's value should be 4, but is 5",
                        "timestamp": "2020-09-24T21:01:02.840126Z",
                        "orig_output": "validate_c1833fdedee0408380c9a059c958948a.hdmx.11 ppem - ERROR - Glyph 100's value should be 4, but is 5",
                        "msg_code": "E1207"
                    },
                    {
                        "subroutine": "validate_c1833fdedee0408380c9a059c958948a.hdmx.12 ppem",
                        "levelname": "ERROR",
                        "message": "Glyph 45's value should be 3, but is 4",
                        "timestamp": "2020-09-24T21:01:02.841265Z",
                        "orig_output": "validate_c1833fdedee0408380c9a059c958948a.hdmx.12 ppem - ERROR - Glyph 45's value should be 3, but is 4",
                        "msg_code": "E1207"
                    },
                    {
                        "subroutine": "validate_c1833fdedee0408380c9a059c958948a.hdmx.12 ppem",
                        "levelname": "ERROR",
                        "message": "Glyph 52's value should be 10, but is 9",
                        "timestamp": "2020-09-24T21:01:02.841323Z",
                        "orig_output": "validate_c1833fdedee0408380c9a059c958948a.hdmx.12 ppem - ERROR - Glyph 52's value should be 10, but is 9",
                        "msg_code": "E1207"
                    },
                    {
                        "subroutine": "validate_c1833fdedee0408380c9a059c958948a.hdmx.12 ppem",
                        "levelname": "ERROR",
                        "message": "Glyph 54's value should be 6, but is 5",
                        "timestamp": "2020-09-24T21:01:02.841372Z",
                        "orig_output": "validate_c1833fdedee0408380c9a059c958948a.hdmx.12 ppem - ERROR - Glyph 54's value should be 6, but is 5",
                        "msg_code": "E1207"
                    },
                    {
                        "subroutine": "validate_c1833fdedee0408380c9a059c958948a.hdmx.12 ppem",
                        "levelname": "ERROR",
                        "message": "Glyph 77's value should be 2, but is 3",
                        "timestamp": "2020-09-24T21:01:02.841428Z",
                        "orig_output": "validate_c1833fdedee0408380c9a059c958948a.hdmx.12 ppem - ERROR - Glyph 77's value should be 2, but is 3",
                        "msg_code": "E1207"
                    },
                    {
                        "subroutine": "validate_c1833fdedee0408380c9a059c958948a.hdmx.12 ppem",
                        "levelname": "ERROR",
                        "message": "Glyph 80's value should be 10, but is 9",
                        "timestamp": "2020-09-24T21:01:02.841475Z",
                        "orig_output": "validate_c1833fdedee0408380c9a059c958948a.hdmx.12 ppem - ERROR - Glyph 80's value should be 10, but is 9",
                        "msg_code": "E1207"
                    },
                    {
                        "subroutine": "validate_c1833fdedee0408380c9a059c958948a.hdmx.13 ppem",
                        "levelname": "ERROR",
                        "message": "Glyph 37's value should be 7, but is 6",
                        "timestamp": "2020-09-24T21:01:02.842678Z",
                        "orig_output": "validate_c1833fdedee0408380c9a059c958948a.hdmx.13 ppem - ERROR - Glyph 37's value should be 7, but is 6",
                        "msg_code": "E1207"
                    },
                    {
                        "subroutine": "validate_c1833fdedee0408380c9a059c958948a.hdmx.13 ppem",
                        "levelname": "ERROR",
                        "message": "Glyph 45's value should be 3, but is 4",
                        "timestamp": "2020-09-24T21:01:02.842759Z",
                        "orig_output": "validate_c1833fdedee0408380c9a059c958948a.hdmx.13 ppem - ERROR - Glyph 45's value should be 3, but is 4",
                        "msg_code": "E1207"
                    },
                    {
                        "subroutine": "validate_c1833fdedee0408380c9a059c958948a.hdmx.13 ppem",
                        "levelname": "ERROR",
                        "message": "Glyph 77's value should be 2, but is 3",
                        "timestamp": "2020-09-24T21:01:02.842834Z",
                        "orig_output": "validate_c1833fdedee0408380c9a059c958948a.hdmx.13 ppem - ERROR - Glyph 77's value should be 2, but is 3",
                        "msg_code": "E1207"
                    },
                    {
                        "subroutine": "validate_c1833fdedee0408380c9a059c958948a.hdmx.13 ppem",
                        "levelname": "ERROR",
                        "message": "Glyph 85's value should be 4, but is 5",
                        "timestamp": "2020-09-24T21:01:02.842886Z",
                        "orig_output": "validate_c1833fdedee0408380c9a059c958948a.hdmx.13 ppem - ERROR - Glyph 85's value should be 4, but is 5",
                        "msg_code": "E1207"
                    },
                    {
                        "subroutine": "validate_c1833fdedee0408380c9a059c958948a.hdmx.14 ppem",
                        "levelname": "ERROR",
                        "message": "Glyph 7's value should be 8, but is 7",
                        "timestamp": "2020-09-24T21:01:02.844024Z",
                        "orig_output": "validate_c1833fdedee0408380c9a059c958948a.hdmx.14 ppem - ERROR - Glyph 7's value should be 8, but is 7",
                        "msg_code": "E1207"
                    },
                    {
                        "subroutine": "validate_c1833fdedee0408380c9a059c958948a.hdmx.14 ppem",
                        "levelname": "ERROR",
                        "message": "Glyph 22's value should be 7, but is 8",
                        "timestamp": "2020-09-24T21:01:02.844086Z",
                        "orig_output": "validate_c1833fdedee0408380c9a059c958948a.hdmx.14 ppem - ERROR - Glyph 22's value should be 7, but is 8",
                        "msg_code": "E1207"
                    },
                    {
                        "subroutine": "validate_c1833fdedee0408380c9a059c958948a.hdmx.14 ppem",
                        "levelname": "ERROR",
                        "message": "Glyph 25's value should be 7, but is 8",
                        "timestamp": "2020-09-24T21:01:02.844137Z",
                        "orig_output": "validate_c1833fdedee0408380c9a059c958948a.hdmx.14 ppem - ERROR - Glyph 25's value should be 7, but is 8",
                        "msg_code": "E1207"
                    },
                    {
                        "subroutine": "validate_c1833fdedee0408380c9a059c958948a.hdmx.14 ppem",
                        "levelname": "ERROR",
                        "message": "Glyph 27's value should be 7, but is 8",
                        "timestamp": "2020-09-24T21:01:02.844184Z",
                        "orig_output": "validate_c1833fdedee0408380c9a059c958948a.hdmx.14 ppem - ERROR - Glyph 27's value should be 7, but is 8",
                        "msg_code": "E1207"
                    },
                    {
                        "subroutine": "validate_c1833fdedee0408380c9a059c958948a.hdmx.14 ppem",
                        "levelname": "ERROR",
                        "message": "Glyph 28's value should be 7, but is 8",
                        "timestamp": "2020-09-24T21:01:02.844230Z",
                        "orig_output": "validate_c1833fdedee0408380c9a059c958948a.hdmx.14 ppem - ERROR - Glyph 28's value should be 7, but is 8",
                        "msg_code": "E1207"
                    },
                    {
                        "subroutine": "validate_c1833fdedee0408380c9a059c958948a.hdmx.14 ppem",
                        "levelname": "ERROR",
                        "message": "Glyph 77's value should be 2, but is 3",
                        "timestamp": "2020-09-24T21:01:02.844299Z",
                        "orig_output": "validate_c1833fdedee0408380c9a059c958948a.hdmx.14 ppem - ERROR - Glyph 77's value should be 2, but is 3",
                        "msg_code": "E1207"
                    },
                    {
                        "subroutine": "validate_c1833fdedee0408380c9a059c958948a.hdmx.15 ppem",
                        "levelname": "ERROR",
                        "message": "Glyph 7's value should be 9, but is 8",
                        "timestamp": "2020-09-24T21:01:02.845527Z",
                        "orig_output": "validate_c1833fdedee0408380c9a059c958948a.hdmx.15 ppem - ERROR - Glyph 7's value should be 9, but is 8",
                        "msg_code": "E1207"
                    },
                    {
                        "subroutine": "validate_c1833fdedee0408380c9a059c958948a.hdmx.15 ppem",
                        "levelname": "ERROR",
                        "message": "Glyph 49's value should be 13, but is 12",
                        "timestamp": "2020-09-24T21:01:02.845611Z",
                        "orig_output": "validate_c1833fdedee0408380c9a059c958948a.hdmx.15 ppem - ERROR - Glyph 49's value should be 13, but is 12",
                        "msg_code": "E1207"
                    },
                    {
                        "subroutine": "validate_c1833fdedee0408380c9a059c958948a.hdmx.15 ppem",
                        "levelname": "ERROR",
                        "message": "Glyph 73's value should be 4, but is 5",
                        "timestamp": "2020-09-24T21:01:02.845670Z",
                        "orig_output": "validate_c1833fdedee0408380c9a059c958948a.hdmx.15 ppem - ERROR - Glyph 73's value should be 4, but is 5",
                        "msg_code": "E1207"
                    },
                    {
                        "subroutine": "validate_c1833fdedee0408380c9a059c958948a.hdmx.16 ppem",
                        "levelname": "ERROR",
                        "message": "Glyph 25's value should be 8, but is 9",
                        "timestamp": "2020-09-24T21:01:02.846822Z",
                        "orig_output": "validate_c1833fdedee0408380c9a059c958948a.hdmx.16 ppem - ERROR - Glyph 25's value should be 8, but is 9",
                        "msg_code": "E1207"
                    },
                    {
                        "subroutine": "validate_c1833fdedee0408380c9a059c958948a.hdmx.16 ppem",
                        "levelname": "ERROR",
                        "message": "Glyph 27's value should be 8, but is 9",
                        "timestamp": "2020-09-24T21:01:02.846877Z",
                        "orig_output": "validate_c1833fdedee0408380c9a059c958948a.hdmx.16 ppem - ERROR - Glyph 27's value should be 8, but is 9",
                        "msg_code": "E1207"
                    },
                    {
                        "subroutine": "validate_c1833fdedee0408380c9a059c958948a.hdmx.16 ppem",
                        "levelname": "ERROR",
                        "message": "Glyph 28's value should be 8, but is 9",
                        "timestamp": "2020-09-24T21:01:02.846925Z",
                        "orig_output": "validate_c1833fdedee0408380c9a059c958948a.hdmx.16 ppem - ERROR - Glyph 28's value should be 8, but is 9",
                        "msg_code": "E1207"
                    },
                    {
                        "subroutine": "validate_c1833fdedee0408380c9a059c958948a.hdmx.16 ppem",
                        "levelname": "ERROR",
                        "message": "Glyph 37's value should be 8, but is 9",
                        "timestamp": "2020-09-24T21:01:02.846975Z",
                        "orig_output": "validate_c1833fdedee0408380c9a059c958948a.hdmx.16 ppem - ERROR - Glyph 37's value should be 8, but is 9",
                        "msg_code": "E1207"
                    },
                    {
                        "subroutine": "validate_c1833fdedee0408380c9a059c958948a.hdmx.16 ppem",
                        "levelname": "ERROR",
                        "message": "Glyph 45's value should be 4, but is 5",
                        "timestamp": "2020-09-24T21:01:02.847024Z",
                        "orig_output": "validate_c1833fdedee0408380c9a059c958948a.hdmx.16 ppem - ERROR - Glyph 45's value should be 4, but is 5",
                        "msg_code": "E1207"
                    },
                    {
                        "subroutine": "validate_c1833fdedee0408380c9a059c958948a.hdmx.16 ppem",
                        "levelname": "ERROR",
                        "message": "Glyph 85's value should be 5, but is 6",
                        "timestamp": "2020-09-24T21:01:02.847087Z",
                        "orig_output": "validate_c1833fdedee0408380c9a059c958948a.hdmx.16 ppem - ERROR - Glyph 85's value should be 5, but is 6",
                        "msg_code": "E1207"
                    },
                    {
                        "subroutine": "validate_c1833fdedee0408380c9a059c958948a.hdmx.16 ppem",
                        "levelname": "ERROR",
                        "message": "Glyph 88's value should be 8, but is 9",
                        "timestamp": "2020-09-24T21:01:02.847133Z",
                        "orig_output": "validate_c1833fdedee0408380c9a059c958948a.hdmx.16 ppem - ERROR - Glyph 88's value should be 8, but is 9",
                        "msg_code": "E1207"
                    },
                    {
                        "subroutine": "validate_c1833fdedee0408380c9a059c958948a.hdmx.16 ppem",
                        "levelname": "ERROR",
                        "message": "Glyph 187's value should be 8, but is 9",
                        "timestamp": "2020-09-24T21:01:02.847222Z",
                        "orig_output": "validate_c1833fdedee0408380c9a059c958948a.hdmx.16 ppem - ERROR - Glyph 187's value should be 8, but is 9",
                        "msg_code": "E1207"
                    },
                    {
                        "subroutine": "validate_c1833fdedee0408380c9a059c958948a.hdmx.16 ppem",
                        "levelname": "ERROR",
                        "message": "Glyph 188's value should be 8, but is 9",
                        "timestamp": "2020-09-24T21:01:02.847267Z",
                        "orig_output": "validate_c1833fdedee0408380c9a059c958948a.hdmx.16 ppem - ERROR - Glyph 188's value should be 8, but is 9",
                        "msg_code": "E1207"
                    },
                    {
                        "subroutine": "validate_c1833fdedee0408380c9a059c958948a.hdmx.16 ppem",
                        "levelname": "ERROR",
                        "message": "Glyph 189's value should be 8, but is 9",
                        "timestamp": "2020-09-24T21:01:02.847311Z",
                        "orig_output": "validate_c1833fdedee0408380c9a059c958948a.hdmx.16 ppem - ERROR - Glyph 189's value should be 8, but is 9",
                        "msg_code": "E1207"
                    },
                    {
                        "subroutine": "validate_c1833fdedee0408380c9a059c958948a.hdmx.16 ppem",
                        "levelname": "ERROR",
                        "message": "Glyph 190's value should be 8, but is 9",
                        "timestamp": "2020-09-24T21:01:02.847356Z",
                        "orig_output": "validate_c1833fdedee0408380c9a059c958948a.hdmx.16 ppem - ERROR - Glyph 190's value should be 8, but is 9",
                        "msg_code": "E1207"
                    },
                    {
                        "subroutine": "validate_c1833fdedee0408380c9a059c958948a.hdmx.17 ppem",
                        "levelname": "ERROR",
                        "message": "Glyph 27's value should be 9, but is 8",
                        "timestamp": "2020-09-24T21:01:02.848439Z",
                        "orig_output": "validate_c1833fdedee0408380c9a059c958948a.hdmx.17 ppem - ERROR - Glyph 27's value should be 9, but is 8",
                        "msg_code": "E1207"
                    },
                    {
                        "subroutine": "validate_c1833fdedee0408380c9a059c958948a.hdmx.17 ppem",
                        "levelname": "ERROR",
                        "message": "Glyph 46's value should be 12, but is 11",
                        "timestamp": "2020-09-24T21:01:02.848502Z",
                        "orig_output": "validate_c1833fdedee0408380c9a059c958948a.hdmx.17 ppem - ERROR - Glyph 46's value should be 12, but is 11",
                        "msg_code": "E1207"
                    },
                    {
                        "subroutine": "validate_c1833fdedee0408380c9a059c958948a.hdmx.17 ppem",
                        "levelname": "ERROR",
                        "message": "Glyph 86's value should be 5, but is 6",
                        "timestamp": "2020-09-24T21:01:02.848568Z",
                        "orig_output": "validate_c1833fdedee0408380c9a059c958948a.hdmx.17 ppem - ERROR - Glyph 86's value should be 5, but is 6",
                        "msg_code": "E1207"
                    },
                    {
                        "subroutine": "validate_c1833fdedee0408380c9a059c958948a.hdmx.18 ppem",
                        "levelname": "ERROR",
                        "message": "Glyph 69's value should be 10, but is 9",
                        "timestamp": "2020-09-24T21:01:02.849733Z",
                        "orig_output": "validate_c1833fdedee0408380c9a059c958948a.hdmx.18 ppem - ERROR - Glyph 69's value should be 10, but is 9",
                        "msg_code": "E1207"
                    },
                    {
                        "subroutine": "validate_c1833fdedee0408380c9a059c958948a.hdmx.18 ppem",
                        "levelname": "ERROR",
                        "message": "Glyph 71's value should be 10, but is 9",
                        "timestamp": "2020-09-24T21:01:02.849787Z",
                        "orig_output": "validate_c1833fdedee0408380c9a059c958948a.hdmx.18 ppem - ERROR - Glyph 71's value should be 10, but is 9",
                        "msg_code": "E1207"
                    },
                    {
                        "subroutine": "validate_c1833fdedee0408380c9a059c958948a.hdmx.18 ppem",
                        "levelname": "ERROR",
                        "message": "Glyph 74's value should be 10, but is 9",
                        "timestamp": "2020-09-24T21:01:02.849837Z",
                        "orig_output": "validate_c1833fdedee0408380c9a059c958948a.hdmx.18 ppem - ERROR - Glyph 74's value should be 10, but is 9",
                        "msg_code": "E1207"
                    },
                    {
                        "subroutine": "validate_c1833fdedee0408380c9a059c958948a.hdmx.18 ppem",
                        "levelname": "ERROR",
                        "message": "Glyph 83's value should be 10, but is 9",
                        "timestamp": "2020-09-24T21:01:02.849887Z",
                        "orig_output": "validate_c1833fdedee0408380c9a059c958948a.hdmx.18 ppem - ERROR - Glyph 83's value should be 10, but is 9",
                        "msg_code": "E1207"
                    },
                    {
                        "subroutine": "validate_c1833fdedee0408380c9a059c958948a.hdmx.18 ppem",
                        "levelname": "ERROR",
                        "message": "Glyph 84's value should be 10, but is 9",
                        "timestamp": "2020-09-24T21:01:02.849932Z",
                        "orig_output": "validate_c1833fdedee0408380c9a059c958948a.hdmx.18 ppem - ERROR - Glyph 84's value should be 10, but is 9",
                        "msg_code": "E1207"
                    },
                    {
                        "subroutine": "validate_c1833fdedee0408380c9a059c958948a.hdmx.19 ppem",
                        "levelname": "ERROR",
                        "message": "Glyph 21's value should be 10, but is 9",
                        "timestamp": "2020-09-24T21:01:02.851075Z",
                        "orig_output": "validate_c1833fdedee0408380c9a059c958948a.hdmx.19 ppem - ERROR - Glyph 21's value should be 10, but is 9",
                        "msg_code": "E1207"
                    },
                    {
                        "subroutine": "validate_c1833fdedee0408380c9a059c958948a.hdmx.19 ppem",
                        "levelname": "ERROR",
                        "message": "Glyph 161's value should be 10, but is 11",
                        "timestamp": "2020-09-24T21:01:02.851195Z",
                        "orig_output": "validate_c1833fdedee0408380c9a059c958948a.hdmx.19 ppem - ERROR - Glyph 161's value should be 10, but is 11",
                        "msg_code": "E1207"
                    },
                    {
                        "subroutine": "validate_c1833fdedee0408380c9a059c958948a.hdmx.20 ppem",
                        "levelname": "ERROR",
                        "message": "Glyph 37's value should be 10, but is 11",
                        "timestamp": "2020-09-24T21:01:02.852296Z",
                        "orig_output": "validate_c1833fdedee0408380c9a059c958948a.hdmx.20 ppem - ERROR - Glyph 37's value should be 10, but is 11",
                        "msg_code": "E1207"
                    },
                    {
                        "subroutine": "validate_c1833fdedee0408380c9a059c958948a.hdmx.20 ppem",
                        "levelname": "ERROR",
                        "message": "Glyph 45's value should be 5, but is 6",
                        "timestamp": "2020-09-24T21:01:02.852352Z",
                        "orig_output": "validate_c1833fdedee0408380c9a059c958948a.hdmx.20 ppem - ERROR - Glyph 45's value should be 5, but is 6",
                        "msg_code": "E1207"
                    },
                    {
                        "subroutine": "validate_c1833fdedee0408380c9a059c958948a.hdmx.20 ppem",
                        "levelname": "ERROR",
                        "message": "Glyph 69's value should be 11, but is 10",
                        "timestamp": "2020-09-24T21:01:02.852414Z",
                        "orig_output": "validate_c1833fdedee0408380c9a059c958948a.hdmx.20 ppem - ERROR - Glyph 69's value should be 11, but is 10",
                        "msg_code": "E1207"
                    },
                    {
                        "subroutine": "validate_c1833fdedee0408380c9a059c958948a.hdmx.20 ppem",
                        "levelname": "ERROR",
                        "message": "Glyph 71's value should be 11, but is 10",
                        "timestamp": "2020-09-24T21:01:02.852465Z",
                        "orig_output": "validate_c1833fdedee0408380c9a059c958948a.hdmx.20 ppem - ERROR - Glyph 71's value should be 11, but is 10",
                        "msg_code": "E1207"
                    },
                    {
                        "subroutine": "validate_c1833fdedee0408380c9a059c958948a.hdmx.20 ppem",
                        "levelname": "ERROR",
                        "message": "Glyph 74's value should be 11, but is 10",
                        "timestamp": "2020-09-24T21:01:02.852515Z",
                        "orig_output": "validate_c1833fdedee0408380c9a059c958948a.hdmx.20 ppem - ERROR - Glyph 74's value should be 11, but is 10",
                        "msg_code": "E1207"
                    },
                    {
                        "subroutine": "validate_c1833fdedee0408380c9a059c958948a.hdmx.20 ppem",
                        "levelname": "ERROR",
                        "message": "Glyph 83's value should be 11, but is 10",
                        "timestamp": "2020-09-24T21:01:02.852568Z",
                        "orig_output": "validate_c1833fdedee0408380c9a059c958948a.hdmx.20 ppem - ERROR - Glyph 83's value should be 11, but is 10",
                        "msg_code": "E1207"
                    },
                    {
                        "subroutine": "validate_c1833fdedee0408380c9a059c958948a.hdmx.20 ppem",
                        "levelname": "ERROR",
                        "message": "Glyph 84's value should be 11, but is 10",
                        "timestamp": "2020-09-24T21:01:02.852628Z",
                        "orig_output": "validate_c1833fdedee0408380c9a059c958948a.hdmx.20 ppem - ERROR - Glyph 84's value should be 11, but is 10",
                        "msg_code": "E1207"
                    },
                    {
                        "subroutine": "validate_c1833fdedee0408380c9a059c958948a.hdmx.21 ppem",
                        "levelname": "ERROR",
                        "message": "Glyph 21's value should be 11, but is 10",
                        "timestamp": "2020-09-24T21:01:02.853813Z",
                        "orig_output": "validate_c1833fdedee0408380c9a059c958948a.hdmx.21 ppem - ERROR - Glyph 21's value should be 11, but is 10",
                        "msg_code": "E1207"
                    },
                    {
                        "subroutine": "validate_c1833fdedee0408380c9a059c958948a.hdmx.21 ppem",
                        "levelname": "ERROR",
                        "message": "Glyph 49's value should be 18, but is 17",
                        "timestamp": "2020-09-24T21:01:02.853900Z",
                        "orig_output": "validate_c1833fdedee0408380c9a059c958948a.hdmx.21 ppem - ERROR - Glyph 49's value should be 18, but is 17",
                        "msg_code": "E1207"
                    },
                    {
                        "subroutine": "validate_c1833fdedee0408380c9a059c958948a.hdmx.21 ppem",
                        "levelname": "ERROR",
                        "message": "Glyph 100's value should be 8, but is 9",
                        "timestamp": "2020-09-24T21:01:02.853977Z",
                        "orig_output": "validate_c1833fdedee0408380c9a059c958948a.hdmx.21 ppem - ERROR - Glyph 100's value should be 8, but is 9",
                        "msg_code": "E1207"
                    },
                    {
                        "subroutine": "validate_c1833fdedee0408380c9a059c958948a.hdmx.21 ppem",
                        "levelname": "ERROR",
                        "message": "Glyph 161's value should be 11, but is 12",
                        "timestamp": "2020-09-24T21:01:02.854058Z",
                        "orig_output": "validate_c1833fdedee0408380c9a059c958948a.hdmx.21 ppem - ERROR - Glyph 161's value should be 11, but is 12",
                        "msg_code": "E1207"
                    },
                    {
                        "subroutine": "validate_c1833fdedee0408380c9a059c958948a.hdmx.22 ppem",
                        "levelname": "ERROR",
                        "message": "Glyph 28's value should be 12, but is 11",
                        "timestamp": "2020-09-24T21:01:02.855305Z",
                        "orig_output": "validate_c1833fdedee0408380c9a059c958948a.hdmx.22 ppem - ERROR - Glyph 28's value should be 12, but is 11",
                        "msg_code": "E1207"
                    },
                    {
                        "subroutine": "validate_c1833fdedee0408380c9a059c958948a.hdmx.22 ppem",
                        "levelname": "ERROR",
                        "message": "Glyph 37's value should be 11, but is 12",
                        "timestamp": "2020-09-24T21:01:02.855378Z",
                        "orig_output": "validate_c1833fdedee0408380c9a059c958948a.hdmx.22 ppem - ERROR - Glyph 37's value should be 11, but is 12",
                        "msg_code": "E1207"
                    },
                    {
                        "subroutine": "validate_c1833fdedee0408380c9a059c958948a.hdmx.22 ppem",
                        "levelname": "ERROR",
                        "message": "Glyph 49's value should be 19, but is 18",
                        "timestamp": "2020-09-24T21:01:02.855434Z",
                        "orig_output": "validate_c1833fdedee0408380c9a059c958948a.hdmx.22 ppem - ERROR - Glyph 49's value should be 19, but is 18",
                        "msg_code": "E1207"
                    },
                    {
                        "subroutine": "validate_c1833fdedee0408380c9a059c958948a.hdmx.23 ppem",
                        "levelname": "ERROR",
                        "message": "Glyph 160's value should be 11, but is 12",
                        "timestamp": "2020-09-24T21:01:02.856655Z",
                        "orig_output": "validate_c1833fdedee0408380c9a059c958948a.hdmx.23 ppem - ERROR - Glyph 160's value should be 11, but is 12",
                        "msg_code": "E1207"
                    },
                    {
                        "subroutine": "validate_c1833fdedee0408380c9a059c958948a.hdmx.24 ppem",
                        "levelname": "ERROR",
                        "message": "Glyph 7's value should be 14, but is 13",
                        "timestamp": "2020-09-24T21:01:02.857761Z",
                        "orig_output": "validate_c1833fdedee0408380c9a059c958948a.hdmx.24 ppem - ERROR - Glyph 7's value should be 14, but is 13",
                        "msg_code": "E1207"
                    },
                    {
                        "subroutine": "validate_c1833fdedee0408380c9a059c958948a.hdmx.24 ppem",
                        "levelname": "ERROR",
                        "message": "Glyph 78's value should be 12, but is 11",
                        "timestamp": "2020-09-24T21:01:02.857850Z",
                        "orig_output": "validate_c1833fdedee0408380c9a059c958948a.hdmx.24 ppem - ERROR - Glyph 78's value should be 12, but is 11",
                        "msg_code": "E1207"
                    },
                    {
                        "subroutine": "validate_c1833fdedee0408380c9a059c958948a.hdmx.25 ppem",
                        "levelname": "ERROR",
                        "message": "Glyph 26's value should be 12, but is 11",
                        "timestamp": "2020-09-24T21:01:02.859006Z",
                        "orig_output": "validate_c1833fdedee0408380c9a059c958948a.hdmx.25 ppem - ERROR - Glyph 26's value should be 12, but is 11",
                        "msg_code": "E1207"
                    },
                    {
                        "subroutine": "validate_c1833fdedee0408380c9a059c958948a.hdmx.26 ppem",
                        "levelname": "ERROR",
                        "message": "Glyph 7's value should be 15, but is 14",
                        "timestamp": "2020-09-24T21:01:02.860152Z",
                        "orig_output": "validate_c1833fdedee0408380c9a059c958948a.hdmx.26 ppem - ERROR - Glyph 7's value should be 15, but is 14",
                        "msg_code": "E1207"
                    },
                    {
                        "subroutine": "validate_c1833fdedee0408380c9a059c958948a.hdmx.26 ppem",
                        "levelname": "ERROR",
                        "message": "Glyph 86's value should be 8, but is 9",
                        "timestamp": "2020-09-24T21:01:02.860245Z",
                        "orig_output": "validate_c1833fdedee0408380c9a059c958948a.hdmx.26 ppem - ERROR - Glyph 86's value should be 8, but is 9",
                        "msg_code": "E1207"
                    },
                    {
                        "subroutine": "validate_c1833fdedee0408380c9a059c958948a.hdmx.27 ppem",
                        "levelname": "ERROR",
                        "message": "Glyph 7's value should be 15, but is 16",
                        "timestamp": "2020-09-24T21:01:02.861355Z",
                        "orig_output": "validate_c1833fdedee0408380c9a059c958948a.hdmx.27 ppem - ERROR - Glyph 7's value should be 15, but is 16",
                        "msg_code": "E1207"
                    },
                    {
                        "subroutine": "validate_c1833fdedee0408380c9a059c958948a.hdmx.27 ppem",
                        "levelname": "ERROR",
                        "message": "Glyph 86's value should be 9, but is 8",
                        "timestamp": "2020-09-24T21:01:02.861445Z",
                        "orig_output": "validate_c1833fdedee0408380c9a059c958948a.hdmx.27 ppem - ERROR - Glyph 86's value should be 9, but is 8",
                        "msg_code": "E1207"
                    },
                    {
                        "subroutine": "validate_c1833fdedee0408380c9a059c958948a.hdmx.28 ppem",
                        "levelname": "ERROR",
                        "message": "Glyph 7's value should be 16, but is 15",
                        "timestamp": "2020-09-24T21:01:02.862662Z",
                        "orig_output": "validate_c1833fdedee0408380c9a059c958948a.hdmx.28 ppem - ERROR - Glyph 7's value should be 16, but is 15",
                        "msg_code": "E1207"
                    },
                    {
                        "subroutine": "validate_c1833fdedee0408380c9a059c958948a.hdmx.28 ppem",
                        "levelname": "ERROR",
                        "message": "Glyph 28's value should be 15, but is 14",
                        "timestamp": "2020-09-24T21:01:02.862742Z",
                        "orig_output": "validate_c1833fdedee0408380c9a059c958948a.hdmx.28 ppem - ERROR - Glyph 28's value should be 15, but is 14",
                        "msg_code": "E1207"
                    },
                    {
                        "subroutine": "validate_c1833fdedee0408380c9a059c958948a.hdmx.28 ppem",
                        "levelname": "ERROR",
                        "message": "Glyph 45's value should be 7, but is 8",
                        "timestamp": "2020-09-24T21:01:02.862801Z",
                        "orig_output": "validate_c1833fdedee0408380c9a059c958948a.hdmx.28 ppem - ERROR - Glyph 45's value should be 7, but is 8",
                        "msg_code": "E1207"
                    },
                    {
                        "subroutine": "validate_c1833fdedee0408380c9a059c958948a.hdmx.28 ppem",
                        "levelname": "ERROR",
                        "message": "Glyph 49's value should be 24, but is 23",
                        "timestamp": "2020-09-24T21:01:02.862851Z",
                        "orig_output": "validate_c1833fdedee0408380c9a059c958948a.hdmx.28 ppem - ERROR - Glyph 49's value should be 24, but is 23",
                        "msg_code": "E1207"
                    },
                    {
                        "subroutine": "validate_c1833fdedee0408380c9a059c958948a.hdmx.29 ppem",
                        "levelname": "ERROR",
                        "message": "Glyph 7's value should be 16, but is 17",
                        "timestamp": "2020-09-24T21:01:02.864044Z",
                        "orig_output": "validate_c1833fdedee0408380c9a059c958948a.hdmx.29 ppem - ERROR - Glyph 7's value should be 16, but is 17",
                        "msg_code": "E1207"
                    },
                    {
                        "subroutine": "validate_c1833fdedee0408380c9a059c958948a.hdmx.29 ppem",
                        "levelname": "ERROR",
                        "message": "Glyph 21's value should be 15, but is 14",
                        "timestamp": "2020-09-24T21:01:02.864113Z",
                        "orig_output": "validate_c1833fdedee0408380c9a059c958948a.hdmx.29 ppem - ERROR - Glyph 21's value should be 15, but is 14",
                        "msg_code": "E1207"
                    },
                    {
                        "subroutine": "validate_c1833fdedee0408380c9a059c958948a.hdmx.29 ppem",
                        "levelname": "ERROR",
                        "message": "Glyph 26's value should be 14, but is 13",
                        "timestamp": "2020-09-24T21:01:02.864164Z",
                        "orig_output": "validate_c1833fdedee0408380c9a059c958948a.hdmx.29 ppem - ERROR - Glyph 26's value should be 14, but is 13",
                        "msg_code": "E1207"
                    },
                    {
                        "subroutine": "validate_c1833fdedee0408380c9a059c958948a.hdmx.29 ppem",
                        "levelname": "ERROR",
                        "message": "Glyph 71's value should be 16, but is 15",
                        "timestamp": "2020-09-24T21:01:02.864243Z",
                        "orig_output": "validate_c1833fdedee0408380c9a059c958948a.hdmx.29 ppem - ERROR - Glyph 71's value should be 16, but is 15",
                        "msg_code": "E1207"
                    },
                    {
                        "subroutine": "validate_c1833fdedee0408380c9a059c958948a.hdmx.29 ppem",
                        "levelname": "ERROR",
                        "message": "Glyph 74's value should be 16, but is 15",
                        "timestamp": "2020-09-24T21:01:02.864296Z",
                        "orig_output": "validate_c1833fdedee0408380c9a059c958948a.hdmx.29 ppem - ERROR - Glyph 74's value should be 16, but is 15",
                        "msg_code": "E1207"
                    },
                    {
                        "subroutine": "validate_c1833fdedee0408380c9a059c958948a.hdmx.29 ppem",
                        "levelname": "ERROR",
                        "message": "Glyph 83's value should be 16, but is 15",
                        "timestamp": "2020-09-24T21:01:02.864351Z",
                        "orig_output": "validate_c1833fdedee0408380c9a059c958948a.hdmx.29 ppem - ERROR - Glyph 83's value should be 16, but is 15",
                        "msg_code": "E1207"
                    },
                    {
                        "subroutine": "validate_c1833fdedee0408380c9a059c958948a.hdmx.29 ppem",
                        "levelname": "ERROR",
                        "message": "Glyph 84's value should be 16, but is 15",
                        "timestamp": "2020-09-24T21:01:02.864397Z",
                        "orig_output": "validate_c1833fdedee0408380c9a059c958948a.hdmx.29 ppem - ERROR - Glyph 84's value should be 16, but is 15",
                        "msg_code": "E1207"
                    },
                    {
                        "subroutine": "validate_c1833fdedee0408380c9a059c958948a.hdmx.30 ppem",
                        "levelname": "ERROR",
                        "message": "Glyph 25's value should be 16, but is 15",
                        "timestamp": "2020-09-24T21:01:02.865638Z",
                        "orig_output": "validate_c1833fdedee0408380c9a059c958948a.hdmx.30 ppem - ERROR - Glyph 25's value should be 16, but is 15",
                        "msg_code": "E1207"
                    },
                    {
                        "subroutine": "validate_c1833fdedee0408380c9a059c958948a.hdmx.30 ppem",
                        "levelname": "ERROR",
                        "message": "Glyph 42's value should be 18, but is 19",
                        "timestamp": "2020-09-24T21:01:02.865717Z",
                        "orig_output": "validate_c1833fdedee0408380c9a059c958948a.hdmx.30 ppem - ERROR - Glyph 42's value should be 18, but is 19",
                        "msg_code": "E1207"
                    },
                    {
                        "subroutine": "validate_c1833fdedee0408380c9a059c958948a.hdmx.9 ppem",
                        "levelname": "ERROR",
                        "message": "Glyph 20's value should be 2, but is 3",
                        "timestamp": "2020-09-24T21:01:02.836562Z",
                        "orig_output": "validate_c1833fdedee0408380c9a059c958948a.hdmx.9 ppem - ERROR - Glyph 20's value should be 2, but is 3",
                        "msg_code": "E1207"
                    },
                    {
                        "subroutine": "validate_c1833fdedee0408380c9a059c958948a.hdmx.9 ppem",
                        "levelname": "ERROR",
                        "message": "Glyph 44's value should be 2, but is 3",
                        "timestamp": "2020-09-24T21:01:02.836704Z",
                        "orig_output": "validate_c1833fdedee0408380c9a059c958948a.hdmx.9 ppem - ERROR - Glyph 44's value should be 2, but is 3",
                        "msg_code": "E1207"
                    },
                    {
                        "subroutine": "validate_c1833fdedee0408380c9a059c958948a.hdmx.9 ppem",
                        "levelname": "ERROR",
                        "message": "Glyph 45's value should be 2, but is 3",
                        "timestamp": "2020-09-24T21:01:02.836762Z",
                        "orig_output": "validate_c1833fdedee0408380c9a059c958948a.hdmx.9 ppem - ERROR - Glyph 45's value should be 2, but is 3",
                        "msg_code": "E1207"
                    },
                    {
                        "subroutine": "validate_c1833fdedee0408380c9a059c958948a.hdmx.9 ppem",
                        "levelname": "ERROR",
                        "message": "Glyph 51's value should be 4, but is 5",
                        "timestamp": "2020-09-24T21:01:02.836815Z",
                        "orig_output": "validate_c1833fdedee0408380c9a059c958948a.hdmx.9 ppem - ERROR - Glyph 51's value should be 4, but is 5",
                        "msg_code": "E1207"
                    },
                    {
                        "subroutine": "validate_c1833fdedee0408380c9a059c958948a.hdmx.9 ppem",
                        "levelname": "ERROR",
                        "message": "Glyph 55's value should be 6, but is 5",
                        "timestamp": "2020-09-24T21:01:02.836866Z",
                        "orig_output": "validate_c1833fdedee0408380c9a059c958948a.hdmx.9 ppem - ERROR - Glyph 55's value should be 6, but is 5",
                        "msg_code": "E1207"
                    },
                    {
                        "subroutine": "validate_c1833fdedee0408380c9a059c958948a.hdmx.9 ppem",
                        "levelname": "ERROR",
                        "message": "Glyph 76's value should be 2, but is 3",
                        "timestamp": "2020-09-24T21:01:02.836921Z",
                        "orig_output": "validate_c1833fdedee0408380c9a059c958948a.hdmx.9 ppem - ERROR - Glyph 76's value should be 2, but is 3",
                        "msg_code": "E1207"
                    },
                    {
                        "subroutine": "validate_c1833fdedee0408380c9a059c958948a.hdmx.9 ppem",
                        "levelname": "ERROR",
                        "message": "Glyph 77's value should be 2, but is 3",
                        "timestamp": "2020-09-24T21:01:02.836967Z",
                        "orig_output": "validate_c1833fdedee0408380c9a059c958948a.hdmx.9 ppem - ERROR - Glyph 77's value should be 2, but is 3",
                        "msg_code": "E1207"
                    },
                    {
                        "subroutine": "validate_c1833fdedee0408380c9a059c958948a.hdmx.9 ppem",
                        "levelname": "ERROR",
                        "message": "Glyph 100's value should be 3, but is 4",
                        "timestamp": "2020-09-24T21:01:02.837023Z",
                        "orig_output": "validate_c1833fdedee0408380c9a059c958948a.hdmx.9 ppem - ERROR - Glyph 100's value should be 3, but is 4",
                        "msg_code": "E1207"
                    },
                    {
                        "subroutine": "validate_c1833fdedee0408380c9a059c958948a.hdmx.9 ppem",
                        "levelname": "ERROR",
                        "message": "Glyph 121's value should be 1, but is 2",
                        "timestamp": "2020-09-24T21:01:02.837079Z",
                        "orig_output": "validate_c1833fdedee0408380c9a059c958948a.hdmx.9 ppem - ERROR - Glyph 121's value should be 1, but is 2",
                        "msg_code": "E1207"
                    },
                    {
                        "subroutine": "validate_c1833fdedee0408380c9a059c958948a.hdmx.9 ppem",
                        "levelname": "ERROR",
                        "message": "Glyph 142's value should be 2, but is 3",
                        "timestamp": "2020-09-24T21:01:02.837134Z",
                        "orig_output": "validate_c1833fdedee0408380c9a059c958948a.hdmx.9 ppem - ERROR - Glyph 142's value should be 2, but is 3",
                        "msg_code": "E1207"
                    },
                    {
                        "subroutine": "validate_c1833fdedee0408380c9a059c958948a.hdmx.9 ppem",
                        "levelname": "ERROR",
                        "message": "Glyph 143's value should be 2, but is 3",
                        "timestamp": "2020-09-24T21:01:02.837180Z",
                        "orig_output": "validate_c1833fdedee0408380c9a059c958948a.hdmx.9 ppem - ERROR - Glyph 143's value should be 2, but is 3",
                        "msg_code": "E1207"
                    },
                    {
                        "subroutine": "validate_c1833fdedee0408380c9a059c958948a.hdmx.9 ppem",
                        "levelname": "ERROR",
                        "message": "Glyph 144's value should be 2, but is 3",
                        "timestamp": "2020-09-24T21:01:02.837225Z",
                        "orig_output": "validate_c1833fdedee0408380c9a059c958948a.hdmx.9 ppem - ERROR - Glyph 144's value should be 2, but is 3",
                        "msg_code": "E1207"
                    },
                    {
                        "subroutine": "validate_c1833fdedee0408380c9a059c958948a.hdmx.9 ppem",
                        "levelname": "ERROR",
                        "message": "Glyph 160's value should be 4, but is 5",
                        "timestamp": "2020-09-24T21:01:02.837277Z",
                        "orig_output": "validate_c1833fdedee0408380c9a059c958948a.hdmx.9 ppem - ERROR - Glyph 160's value should be 4, but is 5",
                        "msg_code": "E1207"
                    },
                    {
                        "subroutine": "validate_c1833fdedee0408380c9a059c958948a.hdmx.9 ppem",
                        "levelname": "ERROR",
                        "message": "Glyph 168's value should be 5, but is 6",
                        "timestamp": "2020-09-24T21:01:02.837326Z",
                        "orig_output": "validate_c1833fdedee0408380c9a059c958948a.hdmx.9 ppem - ERROR - Glyph 168's value should be 5, but is 6",
                        "msg_code": "E1207"
                    },
                    {
                        "subroutine": "validate_c1833fdedee0408380c9a059c958948a.hdmx.9 ppem",
                        "levelname": "ERROR",
                        "message": "Glyph 174's value should be 2, but is 3",
                        "timestamp": "2020-09-24T21:01:02.837374Z",
                        "orig_output": "validate_c1833fdedee0408380c9a059c958948a.hdmx.9 ppem - ERROR - Glyph 174's value should be 2, but is 3",
                        "msg_code": "E1207"
                    },
                    {
                        "subroutine": "validate_c1833fdedee0408380c9a059c958948a.hdmx.9 ppem",
                        "levelname": "ERROR",
                        "message": "Glyph 175's value should be 2, but is 3",
                        "timestamp": "2020-09-24T21:01:02.837419Z",
                        "orig_output": "validate_c1833fdedee0408380c9a059c958948a.hdmx.9 ppem - ERROR - Glyph 175's value should be 2, but is 3",
                        "msg_code": "E1207"
                    },
                    {
                        "subroutine": "validate_c1833fdedee0408380c9a059c958948a.hdmx.9 ppem",
                        "levelname": "ERROR",
                        "message": "Glyph 176's value should be 2, but is 3",
                        "timestamp": "2020-09-24T21:01:02.837464Z",
                        "orig_output": "validate_c1833fdedee0408380c9a059c958948a.hdmx.9 ppem - ERROR - Glyph 176's value should be 2, but is 3",
                        "msg_code": "E1207"
                    },
                    {
                        "subroutine": "validate_c1833fdedee0408380c9a059c958948a.hdmx.9 ppem",
                        "levelname": "ERROR",
                        "message": "Glyph 177's value should be 2, but is 3",
                        "timestamp": "2020-09-24T21:01:02.837509Z",
                        "orig_output": "validate_c1833fdedee0408380c9a059c958948a.hdmx.9 ppem - ERROR - Glyph 177's value should be 2, but is 3",
                        "msg_code": "E1207"
                    },
                    {
                        "subroutine": "validate_c1833fdedee0408380c9a059c958948a.head",
                        "levelname": "ERROR",
                        "message": "The macStyle italic bit is True but post.italicAngle is   0.0",
                        "timestamp": "2020-09-24T21:01:03.075023Z",
                        "orig_output": "validate_c1833fdedee0408380c9a059c958948a.head - ERROR - The macStyle italic bit is True but post.italicAngle is   0.0",
                        "msg_code": "E1316"
                    },
                    {
                        "subroutine": "validate_c1833fdedee0408380c9a059c958948a.LTSH",
                        "levelname": "ERROR",
                        "message": "Glyph 7's value should be 1, but is 30",
                        "timestamp": "2020-09-24T21:00:57.663567Z",
                        "orig_output": "validate_c1833fdedee0408380c9a059c958948a.LTSH - ERROR - Glyph 7's value should be 1, but is 30",
                        "msg_code": "E1804"
                    },
                    {
                        "subroutine": "validate_c1833fdedee0408380c9a059c958948a.LTSH",
                        "levelname": "ERROR",
                        "message": "Glyph 20's value should be 1, but is 10",
                        "timestamp": "2020-09-24T21:00:57.663744Z",
                        "orig_output": "validate_c1833fdedee0408380c9a059c958948a.LTSH - ERROR - Glyph 20's value should be 1, but is 10",
                        "msg_code": "E1804"
                    },
                    {
                        "subroutine": "validate_c1833fdedee0408380c9a059c958948a.LTSH",
                        "levelname": "ERROR",
                        "message": "Glyph 21's value should be 1, but is 30",
                        "timestamp": "2020-09-24T21:00:57.663802Z",
                        "orig_output": "validate_c1833fdedee0408380c9a059c958948a.LTSH - ERROR - Glyph 21's value should be 1, but is 30",
                        "msg_code": "E1804"
                    },
                    {
                        "subroutine": "validate_c1833fdedee0408380c9a059c958948a.LTSH",
                        "levelname": "ERROR",
                        "message": "Glyph 22's value should be 1, but is 15",
                        "timestamp": "2020-09-24T21:00:57.663852Z",
                        "orig_output": "validate_c1833fdedee0408380c9a059c958948a.LTSH - ERROR - Glyph 22's value should be 1, but is 15",
                        "msg_code": "E1804"
                    },
                    {
                        "subroutine": "validate_c1833fdedee0408380c9a059c958948a.LTSH",
                        "levelname": "ERROR",
                        "message": "Glyph 25's value should be 1, but is 31",
                        "timestamp": "2020-09-24T21:00:57.663899Z",
                        "orig_output": "validate_c1833fdedee0408380c9a059c958948a.LTSH - ERROR - Glyph 25's value should be 1, but is 31",
                        "msg_code": "E1804"
                    },
                    {
                        "subroutine": "validate_c1833fdedee0408380c9a059c958948a.LTSH",
                        "levelname": "ERROR",
                        "message": "Glyph 26's value should be 1, but is 30",
                        "timestamp": "2020-09-24T21:00:57.663945Z",
                        "orig_output": "validate_c1833fdedee0408380c9a059c958948a.LTSH - ERROR - Glyph 26's value should be 1, but is 30",
                        "msg_code": "E1804"
                    },
                    {
                        "subroutine": "validate_c1833fdedee0408380c9a059c958948a.LTSH",
                        "levelname": "ERROR",
                        "message": "Glyph 27's value should be 1, but is 18",
                        "timestamp": "2020-09-24T21:00:57.663989Z",
                        "orig_output": "validate_c1833fdedee0408380c9a059c958948a.LTSH - ERROR - Glyph 27's value should be 1, but is 18",
                        "msg_code": "E1804"
                    },
                    {
                        "subroutine": "validate_c1833fdedee0408380c9a059c958948a.LTSH",
                        "levelname": "ERROR",
                        "message": "Glyph 28's value should be 1, but is 29",
                        "timestamp": "2020-09-24T21:00:57.664033Z",
                        "orig_output": "validate_c1833fdedee0408380c9a059c958948a.LTSH - ERROR - Glyph 28's value should be 1, but is 29",
                        "msg_code": "E1804"
                    },
                    {
                        "subroutine": "validate_c1833fdedee0408380c9a059c958948a.LTSH",
                        "levelname": "ERROR",
                        "message": "Glyph 37's value should be 1, but is 23",
                        "timestamp": "2020-09-24T21:00:57.664077Z",
                        "orig_output": "validate_c1833fdedee0408380c9a059c958948a.LTSH - ERROR - Glyph 37's value should be 1, but is 23",
                        "msg_code": "E1804"
                    },
                    {
                        "subroutine": "validate_c1833fdedee0408380c9a059c958948a.LTSH",
                        "levelname": "ERROR",
                        "message": "Glyph 42's value should be 1, but is 31",
                        "timestamp": "2020-09-24T21:00:57.664121Z",
                        "orig_output": "validate_c1833fdedee0408380c9a059c958948a.LTSH - ERROR - Glyph 42's value should be 1, but is 31",
                        "msg_code": "E1804"
                    },
                    {
                        "subroutine": "validate_c1833fdedee0408380c9a059c958948a.LTSH",
                        "levelname": "ERROR",
                        "message": "Glyph 44's value should be 1, but is 10",
                        "timestamp": "2020-09-24T21:00:57.664165Z",
                        "orig_output": "validate_c1833fdedee0408380c9a059c958948a.LTSH - ERROR - Glyph 44's value should be 1, but is 10",
                        "msg_code": "E1804"
                    },
                    {
                        "subroutine": "validate_c1833fdedee0408380c9a059c958948a.LTSH",
                        "levelname": "ERROR",
                        "message": "Glyph 45's value should be 1, but is 29",
                        "timestamp": "2020-09-24T21:00:57.664209Z",
                        "orig_output": "validate_c1833fdedee0408380c9a059c958948a.LTSH - ERROR - Glyph 45's value should be 1, but is 29",
                        "msg_code": "E1804"
                    },
                    {
                        "subroutine": "validate_c1833fdedee0408380c9a059c958948a.LTSH",
                        "levelname": "ERROR",
                        "message": "Glyph 47's value should be 1, but is 11",
                        "timestamp": "2020-09-24T21:00:57.664253Z",
                        "orig_output": "validate_c1833fdedee0408380c9a059c958948a.LTSH - ERROR - Glyph 47's value should be 1, but is 11",
                        "msg_code": "E1804"
                    },
                    {
                        "subroutine": "validate_c1833fdedee0408380c9a059c958948a.LTSH",
                        "levelname": "ERROR",
                        "message": "Glyph 49's value should be 1, but is 29",
                        "timestamp": "2020-09-24T21:00:57.664297Z",
                        "orig_output": "validate_c1833fdedee0408380c9a059c958948a.LTSH - ERROR - Glyph 49's value should be 1, but is 29",
                        "msg_code": "E1804"
                    },
                    {
                        "subroutine": "validate_c1833fdedee0408380c9a059c958948a.LTSH",
                        "levelname": "ERROR",
                        "message": "Glyph 52's value should be 1, but is 13",
                        "timestamp": "2020-09-24T21:00:57.664341Z",
                        "orig_output": "validate_c1833fdedee0408380c9a059c958948a.LTSH - ERROR - Glyph 52's value should be 1, but is 13",
                        "msg_code": "E1804"
                    },
                    {
                        "subroutine": "validate_c1833fdedee0408380c9a059c958948a.LTSH",
                        "levelname": "ERROR",
                        "message": "Glyph 54's value should be 1, but is 13",
                        "timestamp": "2020-09-24T21:00:57.664384Z",
                        "orig_output": "validate_c1833fdedee0408380c9a059c958948a.LTSH - ERROR - Glyph 54's value should be 1, but is 13",
                        "msg_code": "E1804"
                    },
                    {
                        "subroutine": "validate_c1833fdedee0408380c9a059c958948a.LTSH",
                        "levelname": "ERROR",
                        "message": "Glyph 55's value should be 1, but is 11",
                        "timestamp": "2020-09-24T21:00:57.664428Z",
                        "orig_output": "validate_c1833fdedee0408380c9a059c958948a.LTSH - ERROR - Glyph 55's value should be 1, but is 11",
                        "msg_code": "E1804"
                    },
                    {
                        "subroutine": "validate_c1833fdedee0408380c9a059c958948a.LTSH",
                        "levelname": "ERROR",
                        "message": "Glyph 69's value should be 1, but is 21",
                        "timestamp": "2020-09-24T21:00:57.664484Z",
                        "orig_output": "validate_c1833fdedee0408380c9a059c958948a.LTSH - ERROR - Glyph 69's value should be 1, but is 21",
                        "msg_code": "E1804"
                    },
                    {
                        "subroutine": "validate_c1833fdedee0408380c9a059c958948a.LTSH",
                        "levelname": "ERROR",
                        "message": "Glyph 71's value should be 1, but is 30",
                        "timestamp": "2020-09-24T21:00:57.664527Z",
                        "orig_output": "validate_c1833fdedee0408380c9a059c958948a.LTSH - ERROR - Glyph 71's value should be 1, but is 30",
                        "msg_code": "E1804"
                    },
                    {
                        "subroutine": "validate_c1833fdedee0408380c9a059c958948a.LTSH",
                        "levelname": "ERROR",
                        "message": "Glyph 73's value should be 1, but is 16",
                        "timestamp": "2020-09-24T21:00:57.664569Z",
                        "orig_output": "validate_c1833fdedee0408380c9a059c958948a.LTSH - ERROR - Glyph 73's value should be 1, but is 16",
                        "msg_code": "E1804"
                    },
                    {
                        "subroutine": "validate_c1833fdedee0408380c9a059c958948a.LTSH",
                        "levelname": "ERROR",
                        "message": "Glyph 74's value should be 1, but is 30",
                        "timestamp": "2020-09-24T21:00:57.664611Z",
                        "orig_output": "validate_c1833fdedee0408380c9a059c958948a.LTSH - ERROR - Glyph 74's value should be 1, but is 30",
                        "msg_code": "E1804"
                    },
                    {
                        "subroutine": "validate_c1833fdedee0408380c9a059c958948a.LTSH",
                        "levelname": "ERROR",
                        "message": "Glyph 76's value should be 1, but is 10",
                        "timestamp": "2020-09-24T21:00:57.664653Z",
                        "orig_output": "validate_c1833fdedee0408380c9a059c958948a.LTSH - ERROR - Glyph 76's value should be 1, but is 10",
                        "msg_code": "E1804"
                    },
                    {
                        "subroutine": "validate_c1833fdedee0408380c9a059c958948a.LTSH",
                        "levelname": "ERROR",
                        "message": "Glyph 77's value should be 1, but is 15",
                        "timestamp": "2020-09-24T21:00:57.664695Z",
                        "orig_output": "validate_c1833fdedee0408380c9a059c958948a.LTSH - ERROR - Glyph 77's value should be 1, but is 15",
                        "msg_code": "E1804"
                    },
                    {
                        "subroutine": "validate_c1833fdedee0408380c9a059c958948a.LTSH",
                        "levelname": "ERROR",
                        "message": "Glyph 78's value should be 2, but is 25",
                        "timestamp": "2020-09-24T21:00:57.664745Z",
                        "orig_output": "validate_c1833fdedee0408380c9a059c958948a.LTSH - ERROR - Glyph 78's value should be 2, but is 25",
                        "msg_code": "E1804"
                    },
                    {
                        "subroutine": "validate_c1833fdedee0408380c9a059c958948a.LTSH",
                        "levelname": "ERROR",
                        "message": "Glyph 80's value should be 1, but is 13",
                        "timestamp": "2020-09-24T21:00:57.664805Z",
                        "orig_output": "validate_c1833fdedee0408380c9a059c958948a.LTSH - ERROR - Glyph 80's value should be 1, but is 13",
                        "msg_code": "E1804"
                    },
                    {
                        "subroutine": "validate_c1833fdedee0408380c9a059c958948a.LTSH",
                        "levelname": "ERROR",
                        "message": "Glyph 83's value should be 1, but is 30",
                        "timestamp": "2020-09-24T21:00:57.664849Z",
                        "orig_output": "validate_c1833fdedee0408380c9a059c958948a.LTSH - ERROR - Glyph 83's value should be 1, but is 30",
                        "msg_code": "E1804"
                    },
                    {
                        "subroutine": "validate_c1833fdedee0408380c9a059c958948a.LTSH",
                        "levelname": "ERROR",
                        "message": "Glyph 84's value should be 1, but is 30",
                        "timestamp": "2020-09-24T21:00:57.664893Z",
                        "orig_output": "validate_c1833fdedee0408380c9a059c958948a.LTSH - ERROR - Glyph 84's value should be 1, but is 30",
                        "msg_code": "E1804"
                    },
                    {
                        "subroutine": "validate_c1833fdedee0408380c9a059c958948a.LTSH",
                        "levelname": "ERROR",
                        "message": "Glyph 85's value should be 1, but is 17",
                        "timestamp": "2020-09-24T21:00:57.664937Z",
                        "orig_output": "validate_c1833fdedee0408380c9a059c958948a.LTSH - ERROR - Glyph 85's value should be 1, but is 17",
                        "msg_code": "E1804"
                    },
                    {
                        "subroutine": "validate_c1833fdedee0408380c9a059c958948a.LTSH",
                        "levelname": "ERROR",
                        "message": "Glyph 88's value should be 1, but is 17",
                        "timestamp": "2020-09-24T21:00:57.664980Z",
                        "orig_output": "validate_c1833fdedee0408380c9a059c958948a.LTSH - ERROR - Glyph 88's value should be 1, but is 17",
                        "msg_code": "E1804"
                    },
                    {
                        "subroutine": "validate_c1833fdedee0408380c9a059c958948a.LTSH",
                        "levelname": "ERROR",
                        "message": "Glyph 100's value should be 1, but is 22",
                        "timestamp": "2020-09-24T21:00:57.665023Z",
                        "orig_output": "validate_c1833fdedee0408380c9a059c958948a.LTSH - ERROR - Glyph 100's value should be 1, but is 22",
                        "msg_code": "E1804"
                    },
                    {
                        "subroutine": "validate_c1833fdedee0408380c9a059c958948a.LTSH",
                        "levelname": "ERROR",
                        "message": "Glyph 121's value should be 1, but is 10",
                        "timestamp": "2020-09-24T21:00:57.665066Z",
                        "orig_output": "validate_c1833fdedee0408380c9a059c958948a.LTSH - ERROR - Glyph 121's value should be 1, but is 10",
                        "msg_code": "E1804"
                    },
                    {
                        "subroutine": "validate_c1833fdedee0408380c9a059c958948a.LTSH",
                        "levelname": "ERROR",
                        "message": "Glyph 142's value should be 1, but is 10",
                        "timestamp": "2020-09-24T21:00:57.665109Z",
                        "orig_output": "validate_c1833fdedee0408380c9a059c958948a.LTSH - ERROR - Glyph 142's value should be 1, but is 10",
                        "msg_code": "E1804"
                    },
                    {
                        "subroutine": "validate_c1833fdedee0408380c9a059c958948a.LTSH",
                        "levelname": "ERROR",
                        "message": "Glyph 143's value should be 1, but is 10",
                        "timestamp": "2020-09-24T21:00:57.665152Z",
                        "orig_output": "validate_c1833fdedee0408380c9a059c958948a.LTSH - ERROR - Glyph 143's value should be 1, but is 10",
                        "msg_code": "E1804"
                    },
                    {
                        "subroutine": "validate_c1833fdedee0408380c9a059c958948a.LTSH",
                        "levelname": "ERROR",
                        "message": "Glyph 144's value should be 1, but is 10",
                        "timestamp": "2020-09-24T21:00:57.665196Z",
                        "orig_output": "validate_c1833fdedee0408380c9a059c958948a.LTSH - ERROR - Glyph 144's value should be 1, but is 10",
                        "msg_code": "E1804"
                    },
                    {
                        "subroutine": "validate_c1833fdedee0408380c9a059c958948a.LTSH",
                        "levelname": "ERROR",
                        "message": "Glyph 160's value should be 2, but is 24",
                        "timestamp": "2020-09-24T21:00:57.665239Z",
                        "orig_output": "validate_c1833fdedee0408380c9a059c958948a.LTSH - ERROR - Glyph 160's value should be 2, but is 24",
                        "msg_code": "E1804"
                    },
                    {
                        "subroutine": "validate_c1833fdedee0408380c9a059c958948a.LTSH",
                        "levelname": "ERROR",
                        "message": "Glyph 161's value should be 1, but is 22",
                        "timestamp": "2020-09-24T21:00:57.665282Z",
                        "orig_output": "validate_c1833fdedee0408380c9a059c958948a.LTSH - ERROR - Glyph 161's value should be 1, but is 22",
                        "msg_code": "E1804"
                    },
                    {
                        "subroutine": "validate_c1833fdedee0408380c9a059c958948a.LTSH",
                        "levelname": "ERROR",
                        "message": "Glyph 168's value should be 1, but is 10",
                        "timestamp": "2020-09-24T21:00:57.665326Z",
                        "orig_output": "validate_c1833fdedee0408380c9a059c958948a.LTSH - ERROR - Glyph 168's value should be 1, but is 10",
                        "msg_code": "E1804"
                    },
                    {
                        "subroutine": "validate_c1833fdedee0408380c9a059c958948a.LTSH",
                        "levelname": "ERROR",
                        "message": "Glyph 174's value should be 1, but is 10",
                        "timestamp": "2020-09-24T21:00:57.665368Z",
                        "orig_output": "validate_c1833fdedee0408380c9a059c958948a.LTSH - ERROR - Glyph 174's value should be 1, but is 10",
                        "msg_code": "E1804"
                    },
                    {
                        "subroutine": "validate_c1833fdedee0408380c9a059c958948a.LTSH",
                        "levelname": "ERROR",
                        "message": "Glyph 175's value should be 1, but is 10",
                        "timestamp": "2020-09-24T21:00:57.665412Z",
                        "orig_output": "validate_c1833fdedee0408380c9a059c958948a.LTSH - ERROR - Glyph 175's value should be 1, but is 10",
                        "msg_code": "E1804"
                    },
                    {
                        "subroutine": "validate_c1833fdedee0408380c9a059c958948a.LTSH",
                        "levelname": "ERROR",
                        "message": "Glyph 176's value should be 1, but is 10",
                        "timestamp": "2020-09-24T21:00:57.665455Z",
                        "orig_output": "validate_c1833fdedee0408380c9a059c958948a.LTSH - ERROR - Glyph 176's value should be 1, but is 10",
                        "msg_code": "E1804"
                    },
                    {
                        "subroutine": "validate_c1833fdedee0408380c9a059c958948a.LTSH",
                        "levelname": "ERROR",
                        "message": "Glyph 177's value should be 1, but is 10",
                        "timestamp": "2020-09-24T21:00:57.665498Z",
                        "orig_output": "validate_c1833fdedee0408380c9a059c958948a.LTSH - ERROR - Glyph 177's value should be 1, but is 10",
                        "msg_code": "E1804"
                    },
                    {
                        "subroutine": "validate_c1833fdedee0408380c9a059c958948a.LTSH",
                        "levelname": "ERROR",
                        "message": "Glyph 187's value should be 1, but is 17",
                        "timestamp": "2020-09-24T21:00:57.665541Z",
                        "orig_output": "validate_c1833fdedee0408380c9a059c958948a.LTSH - ERROR - Glyph 187's value should be 1, but is 17",
                        "msg_code": "E1804"
                    },
                    {
                        "subroutine": "validate_c1833fdedee0408380c9a059c958948a.LTSH",
                        "levelname": "ERROR",
                        "message": "Glyph 188's value should be 1, but is 17",
                        "timestamp": "2020-09-24T21:00:57.665584Z",
                        "orig_output": "validate_c1833fdedee0408380c9a059c958948a.LTSH - ERROR - Glyph 188's value should be 1, but is 17",
                        "msg_code": "E1804"
                    },
                    {
                        "subroutine": "validate_c1833fdedee0408380c9a059c958948a.LTSH",
                        "levelname": "ERROR",
                        "message": "Glyph 189's value should be 1, but is 17",
                        "timestamp": "2020-09-24T21:00:57.665628Z",
                        "orig_output": "validate_c1833fdedee0408380c9a059c958948a.LTSH - ERROR - Glyph 189's value should be 1, but is 17",
                        "msg_code": "E1804"
                    },
                    {
                        "subroutine": "validate_c1833fdedee0408380c9a059c958948a.LTSH",
                        "levelname": "ERROR",
                        "message": "Glyph 190's value should be 1, but is 17",
                        "timestamp": "2020-09-24T21:00:57.665671Z",
                        "orig_output": "validate_c1833fdedee0408380c9a059c958948a.LTSH - ERROR - Glyph 190's value should be 1, but is 17",
                        "msg_code": "E1804"
                    },
                    {
                        "subroutine": "validate_c1833fdedee0408380c9a059c958948a.OS_2.unicodeRanges",
                        "levelname": "ERROR",
                        "message": "Unicode range 'hasCJKIdeographs' claimed to be present but is not.",
                        "timestamp": "2020-09-24T21:00:58.597027Z",
                        "orig_output": "validate_c1833fdedee0408380c9a059c958948a.OS_2.unicodeRanges - ERROR - Unicode range 'hasCJKIdeographs' claimed to be present but is not.",
                        "msg_code": "E2113"
                    },
                    {
                        "subroutine": "validate_c1833fdedee0408380c9a059c958948a.OS_2.unicodeRanges",
                        "levelname": "ERROR",
                        "message": "Unicode range 'hasPlane1516Private' claimed to be present but is not.",
                        "timestamp": "2020-09-24T21:00:58.597150Z",
                        "orig_output": "validate_c1833fdedee0408380c9a059c958948a.OS_2.unicodeRanges - ERROR - Unicode range 'hasPlane1516Private' claimed to be present but is not.",
                        "msg_code": "E2113"
                    },
                    {
                        "subroutine": "validate_c1833fdedee0408380c9a059c958948a.OS_2.unicodeRanges",
                        "levelname": "ERROR",
                        "message": "Unicode range 'hasTags' claimed to be present but is not.",
                        "timestamp": "2020-09-24T21:00:58.597264Z",
                        "orig_output": "validate_c1833fdedee0408380c9a059c958948a.OS_2.unicodeRanges - ERROR - Unicode range 'hasTags' claimed to be present but is not.",
                        "msg_code": "E2113"
                    },
                    {
                        "subroutine": "validate_c1833fdedee0408380c9a059c958948a.post",
                        "levelname": "ERROR",
                        "message": "Zero italic angle but head.macStyle.italic is True.",
                        "timestamp": "2020-09-24T21:01:05.361704Z",
                        "orig_output": "validate_c1833fdedee0408380c9a059c958948a.post - ERROR - Zero italic angle but head.macStyle.italic is True.",
                        "msg_code": "E2310"
                    }
                ]
            }
        }
    ],
    "skipped": [],
    "fontio3_version": "3.7.20200604.317848rc4",
    "fontvalidator_version": "20200305.1",
    "runningTime": 20610,
    "completedDate": "2020-09-24 21:01:07.167394"
}